{
  "schema_version": "1.0",
  "dataset": "bistro",
  "id": "Paris_Wine_Cooler_01A",
  "name": "Paris_Wine_Cooler_01A",
  "export_name": "Paris_Wine_Cooler_01A",
  "files": {
    "obj": "data/assets/Paris_Wine_Cooler_01A/Paris_Wine_Cooler_01A.obj",
    "preview": "data/assets/Paris_Wine_Cooler_01A/Paris_Wine_Cooler_01A.png"
  },
  "placement": {
    "class": "tabletop",
    "enabled": true,
    "support": [
      "table",
      "counter"
    ],
    "weight": 1.0
  },
  "geometry": {
    "units": "meter",
    "size": {
      "x": 0.41411,
      "y": 0.414288,
      "z": 0.293023
    },
    "bbox": {
      "min": [
        -0.207055,
        -0.207144,
        0.0
      ],
      "max": [
        0.207055,
        0.207144,
        0.293023
      ]
    }
  },
  "normalization": {
    "coordinate_system": {
      "right": "+X",
      "forward": "+Y",
      "up": "+Z"
    },
    "grounded": true,
    "xy_origin": "bbox_center",
    "orientation": "principal_horizontal_axis_to_+Y",
    "applied_z_rotation_radians": 0.0
  },
  "materials": {
    "sionna": [
      "itu-glass"
    ],
    "source_to_sionna": [
      {
        "source": "Metal_Chrome1",
        "sionna": "itu-glass",
        "itu_type": "glass",
        "confidence": "high"
      }
    ]
  }
}
