{
  "schema_version": "1.0",
  "dataset": "bistro",
  "id": "Cotton_Placemat",
  "name": "Cotton_Placemat",
  "export_name": "Cotton_Placemat",
  "files": {
    "obj": "data/assets/Cotton_Placemat/Cotton_Placemat.obj",
    "preview": "data/assets/Cotton_Placemat/Cotton_Placemat.png"
  },
  "placement": {
    "class": "tabletop",
    "enabled": true,
    "support": [
      "table",
      "counter"
    ],
    "weight": 1.0
  },
  "geometry": {
    "units": "meter",
    "size": {
      "x": 0.331802,
      "y": 0.531543,
      "z": 0.001394
    },
    "bbox": {
      "min": [
        -0.165901,
        -0.265771,
        0.0
      ],
      "max": [
        0.165901,
        0.265771,
        0.001394
      ]
    }
  },
  "normalization": {
    "coordinate_system": {
      "right": "+X",
      "forward": "+Y",
      "up": "+Z"
    },
    "grounded": true,
    "xy_origin": "bbox_center",
    "orientation": "principal_horizontal_axis_to_+Y",
    "applied_z_rotation_radians": -2.06919866
  },
  "materials": {
    "sionna": [
      "itu-wood"
    ],
    "source_to_sionna": [
      {
        "source": "Paris_Table_cloth_01",
        "sionna": "itu-wood",
        "itu_type": "wood",
        "confidence": "medium"
      }
    ]
  }
}
